titantuner/__init__.py
titantuner/__main__.py
titantuner/app.py
titantuner/autotune.py
titantuner/dataset.py
titantuner/data/ta_20200601T12Z.txt
titantuner-0.1.1.dist-info/METADATA
titantuner-0.1.1.dist-info/WHEEL
titantuner-0.1.1.dist-info/entry_points.txt
titantuner-0.1.1.dist-info/top_level.txt
titantuner-0.1.1.dist-info/RECORD
