Metadata-Version: 2.1
Name: titantuner
Version: 0.1.1
Summary: A package for tuning quality control parameters in titanlib
Author-email: Thomas Nipen <thomasnn@met.no>
License: MIT
Keywords: meteorology,observations,quality control
Classifier: Development Status :: 3 - Alpha
Classifier: Programming Language :: Python :: 3
Requires-Dist: bokeh <3
Requires-Dist: matplotlib
Requires-Dist: numpy
Requires-Dist: scipy
Requires-Dist: titanlib >=0.3.3
